rawautoparams/__init__.py
rawautoparams/rawautoparams.py
rawautoparams-0.0.5.dist-info/METADATA
rawautoparams-0.0.5.dist-info/WHEEL
rawautoparams-0.0.5.dist-info/top_level.txt
rawautoparams-0.0.5.dist-info/RECORD
