Metadata-Version: 2.1
Name: rawautoparams
Version: 0.0.5
Summary: Thermo/Finnigan .raw file format parameters reader
Home-page: https://gitlab.science.ru.nl/jzelenka/rawautoparams
Author: Jan Zelenka
Author-email: 3yanyanyan@gmail.com
License: UNKNOWN
Platform: OS Independent
Classifier: Programming Language :: Python :: 3
Classifier: Operating System :: OS Independent
Classifier: Development Status :: 3 - Alpha
Classifier: Intended Audience :: Science/Research
Classifier: Topic :: Scientific/Engineering :: Chemistry
Requires-Dist: numpy
Requires-Dist: rawprasslib
